geovalidator/__init__.py
geovalidator/utils.py
geovalidator/validators/__init__.py
geovalidator/validators/completeness.py
geovalidator/validators/crs.py
geovalidator/validators/topology.py
polyvalidator/__init__.py
polyvalidator/utils.py
polyvalidator/validators/__init__.py
polyvalidator/validators/completeness.py
polyvalidator/validators/crs.py
polyvalidator/validators/topology.py
poly_validator-0.1.0.dist-info/LICENSE
poly_validator-0.1.0.dist-info/METADATA
poly_validator-0.1.0.dist-info/WHEEL
poly_validator-0.1.0.dist-info/top_level.txt
poly_validator-0.1.0.dist-info/RECORD
