Metadata-Version: 2.1
Name: poly-validator
Version: 0.1.0
Summary: GA tool for validating geospatial data with topology checks, coordinate system validation, and more.
Home-page: https://github.com/billyz313/Geospatial-Data-Validation-Tool
Author: BillyZ
Author-email: billyz313@gmail.com
Classifier: Development Status :: 4 - Beta
Classifier: Intended Audience :: Developers
Classifier: License :: OSI Approved :: MIT License
Classifier: Programming Language :: Python :: 3
Classifier: Programming Language :: Python :: 3.8
Classifier: Topic :: Software Development :: Libraries :: Python Modules
Requires-Python: >=3.11
License-File: LICENSE
Requires-Dist: geopandas
Requires-Dist: shapely
Requires-Dist: pyproj
Requires-Dist: pyogrio
Requires-Dist: fiona
